lamina_llm_serve/CLAUDE.md
lamina_llm_serve/__init__.py
lamina_llm_serve/backends.py
lamina_llm_serve/downloader.py
lamina_llm_serve/model_manager.py
lamina_llm_serve/server.py
lamina_llm_serve-0.2.0.dist-info/METADATA
lamina_llm_serve-0.2.0.dist-info/WHEEL
lamina_llm_serve-0.2.0.dist-info/entry_points.txt
lamina_llm_serve-0.2.0.dist-info/RECORD
