Metadata-Version: 2.4
Name: lamina-llm-serve
Version: 0.2.0
Summary: Centralized model caching and serving layer for Lamina OS
Project-URL: Homepage, https://github.com/benaskins/lamina-os
Project-URL: Documentation, https://github.com/benaskins/lamina-os/blob/main/docs/
Project-URL: Repository, https://github.com/benaskins/lamina-os
Project-URL: Issues, https://github.com/benaskins/lamina-os/issues
Author-email: Ben Askins <human@getlamina.ai>, Lamina High Council <council@getlamina.ai>
License: MPL-2.0
Keywords: ai-backends,caching,lamina,llm,model-serving
Classifier: Development Status :: 3 - Alpha
Classifier: Intended Audience :: Developers
Classifier: License :: OSI Approved :: Mozilla Public License 2.0 (MPL 2.0)
Classifier: Programming Language :: Python :: 3
Classifier: Programming Language :: Python :: 3.11
Classifier: Programming Language :: Python :: 3.12
Classifier: Programming Language :: Python :: 3.13
Classifier: Topic :: Scientific/Engineering :: Artificial Intelligence
Classifier: Topic :: Software Development :: Libraries :: Python Modules
Requires-Python: >=3.11
Requires-Dist: click>=8.1.7
Requires-Dist: flask>=3.1.0
Requires-Dist: huggingface-hub>=0.32.0
Requires-Dist: pydantic>=2.10.0
Requires-Dist: python-dotenv>=1.0.1
Requires-Dist: pyyaml>=6.0.2
Requires-Dist: requests>=2.32.0
Requires-Dist: rich>=13.9.0
Requires-Dist: tqdm>=4.67.0
Requires-Dist: transformers>=4.47.0
Provides-Extra: all
Requires-Dist: bandit>=1.8.0; extra == 'all'
Requires-Dist: black>=24.10.0; extra == 'all'
Requires-Dist: httpx>=0.28.0; extra == 'all'
Requires-Dist: ipython>=8.30.0; extra == 'all'
Requires-Dist: isort>=5.13.0; extra == 'all'
Requires-Dist: jupyter>=1.1.1; extra == 'all'
Requires-Dist: mypy>=1.13.0; extra == 'all'
Requires-Dist: pre-commit>=4.0.0; extra == 'all'
Requires-Dist: pytest-cov>=6.0.0; extra == 'all'
Requires-Dist: pytest-mock>=3.14.0; extra == 'all'
Requires-Dist: pytest>=8.3.0; extra == 'all'
Requires-Dist: ruff>=0.8.0; extra == 'all'
Provides-Extra: backends
Provides-Extra: dev
Requires-Dist: bandit>=1.8.0; extra == 'dev'
Requires-Dist: black>=24.10.0; extra == 'dev'
Requires-Dist: httpx>=0.28.0; extra == 'dev'
Requires-Dist: ipython>=8.30.0; extra == 'dev'
Requires-Dist: isort>=5.13.0; extra == 'dev'
Requires-Dist: jupyter>=1.1.1; extra == 'dev'
Requires-Dist: mypy>=1.13.0; extra == 'dev'
Requires-Dist: pre-commit>=4.0.0; extra == 'dev'
Requires-Dist: pytest-cov>=6.0.0; extra == 'dev'
Requires-Dist: pytest-mock>=3.14.0; extra == 'dev'
Requires-Dist: pytest>=8.3.0; extra == 'dev'
Requires-Dist: ruff>=0.8.0; extra == 'dev'
